cert_quiz_app/GUI.py
cert_quiz_app/__init__.py
ThePocketTrainer-0.0.3.dist-info/METADATA
ThePocketTrainer-0.0.3.dist-info/WHEEL
ThePocketTrainer-0.0.3.dist-info/top_level.txt
ThePocketTrainer-0.0.3.dist-info/RECORD
